songbird_py-0.1.7.dist-info/METADATA
songbird_py-0.1.7.dist-info/WHEEL
songbird_py-0.1.7.dist-info/license_files/LICENSE
songbird/exceptions.py
songbird/helpers.py
songbird/hikari.py
songbird/pincer.py
songbird/playlist.py
songbird/py.typed
songbird/queue.py
songbird/songbird.pyi
songbird/voicebox_base.py
songbird/__init__.py
songbird/songbird.cp38-win_amd64.pyd
songbird_py-0.1.7.dist-info/RECORD
