Metadata-Version: 2.1
Name: songbird-py
Version: 0.1.7
Classifier: Programming Language :: Rust
Classifier: Programming Language :: Python :: Implementation :: CPython
Classifier: Programming Language :: Python :: Implementation :: PyPy
Classifier: License :: OSI Approved :: GNU General Public License v2 (GPLv2)
Classifier: Operating System :: OS Independent
Requires-Dist: yt-dlp>=2021.12.1
Requires-Dist: hikari; extra == 'hikari'
Requires-Dist: pincer; extra == 'pincer'
Provides-Extra: hikari
Provides-Extra: pincer
License-File: LICENSE
Summary: A Discord voice library using Python Songbird bindings.
Requires-Python: >=3.8
Project-URL: Docs, https://songbird-py.readthedocs.io/en/latest/
Project-URL: Bug Tracker, https://github.com/Lunarmagpie/Songbird-Py/issues
Project-URL: GitHub, https://github.com/Lunarmagpie/Songbird-Py
